starform/__init__.py
starform/formation.py
starform/star.py
starform/classic/__init__.py
starform/classic/cstar.py
starform-0.0.1.dist-info/LICENSE
starform-0.0.1.dist-info/METADATA
starform-0.0.1.dist-info/WHEEL
starform-0.0.1.dist-info/top_level.txt
starform-0.0.1.dist-info/RECORD
