Metadata-Version: 2.1
Name: starform
Version: 0.0.1
Summary: StarForm is a Python library to quickly develop clean modular models/pipelines.
Home-page: https://github.com/TommyDong1998/StarFormation
Author: Tommy Dong
Author-email: tommydong1998@gmail.com
License: UNKNOWN
Platform: UNKNOWN
Requires-Dist: pathos
